LICENSE
MANIFEST.in
README.rst
setup.py
django_mauveinternet.egg-info/PKG-INFO
django_mauveinternet.egg-info/SOURCES.txt
django_mauveinternet.egg-info/dependency_links.txt
django_mauveinternet.egg-info/not-zip-safe
django_mauveinternet.egg-info/requires.txt
django_mauveinternet.egg-info/top_level.txt
mauveinternet/__init__.py
mauveinternet/context_processors.py
mauveinternet/csvresponse.py
mauveinternet/decorators.py
mauveinternet/formmail.py
mauveinternet/forms.py
mauveinternet/middleware.py
mauveinternet/models.py
mauveinternet/money.py
mauveinternet/shortcuts.py
mauveinternet/thumbnail.py
mauveinternet/calendar/__init__.py
mauveinternet/calendar/month.py
mauveinternet/calendar/week.py
mauveinternet/content_scoring/__init__.py
mauveinternet/content_scoring/widgets.py
mauveinternet/content_scoring/templatetags/__init__.py
mauveinternet/content_scoring/templatetags/content_scoring.py
mauveinternet/devtools/__init__.py
mauveinternet/devtools/models.py
mauveinternet/devtools/views.py
mauveinternet/devtools/management/__init__.py
mauveinternet/devtools/management/commands/__init__.py
mauveinternet/devtools/management/commands/modelmap.py
mauveinternet/devtools/management/commands/show_template_tree.py
mauveinternet/emailing/__init__.py
mauveinternet/emailing/admin.py
mauveinternet/emailing/models.py
mauveinternet/emailing/template.py
mauveinternet/emailing/views.py
mauveinternet/help/__init__.py
mauveinternet/help/admin.py
mauveinternet/help/models.py
mauveinternet/help/urls.py
mauveinternet/help/views.py
mauveinternet/help/templates/help/inline_help.html
mauveinternet/help/templates/help/quick_help.html
mauveinternet/help/templatetags/__init__.py
mauveinternet/help/templatetags/help.py
mauveinternet/markdown/__init__.py
mauveinternet/markdown/util.py
mauveinternet/markdown/views.py
mauveinternet/markdown/static/mimarkdown/css/markdownarea.css
mauveinternet/markdown/static/mimarkdown/icons/bold.png
mauveinternet/markdown/static/mimarkdown/icons/heading.png
mauveinternet/markdown/static/mimarkdown/icons/help.png
mauveinternet/markdown/static/mimarkdown/icons/italic.png
mauveinternet/markdown/static/mimarkdown/icons/link.png
mauveinternet/markdown/static/mimarkdown/icons/ordered-list.png
