Metadata-Version: 1.0
Name: django-mauveinternet
Version: 1.0.1
Summary: A collection of extensions for Django developed by Mauve Internet
Home-page: http://pypi.python.org/pypi/django-mauveinternet
Author: Daniel Pope
Author-email: dan@mauveinternet.co.uk
License: UNKNOWN
Platform: UNKNOWN
